myrpl_cli/__init__.py
myrpl_cli/api.py
myrpl_cli/credential_manager.py
myrpl_cli/errors.py
myrpl_cli/main.py
myrpl_cli/models.py
myrpl_cli/myrpl.py
myrpl_cli-1.0.0.dist-info/LICENSE
myrpl_cli-1.0.0.dist-info/METADATA
myrpl_cli-1.0.0.dist-info/WHEEL
myrpl_cli-1.0.0.dist-info/entry_points.txt
myrpl_cli-1.0.0.dist-info/RECORD
