Metadata-Version: 2.1
Name: myrpl-cli
Version: 1.0.0
Summary: A script to fetch and save course activities from myrpl.ar
Author: tcorzo
Requires-Python: >=3.10,<4.0
Classifier: Programming Language :: Python :: 3
Classifier: Programming Language :: Python :: 3.10
Classifier: Programming Language :: Python :: 3.11
Requires-Dist: keyring (>=25.4.1,<26.0.0)
Requires-Dist: keyrings-cryptfile (>=1.3.9,<2.0.0)
Requires-Dist: pydantic (>=2.9.2,<3.0.0)
Requires-Dist: pytest (>=8.3.3,<9.0.0)
Requires-Dist: python-dotenv (>=1.0.1,<2.0.0)
Requires-Dist: requests (>=2.25.1,<3.0.0)
Requires-Dist: requests-toolbelt (>=1.0.0,<2.0.0)
Requires-Dist: timeout-decorator (>=0.5.0,<0.6.0)
Requires-Dist: toml (>=0.10.2,<0.11.0)
Requires-Dist: tqdm (>=4.66.5,<5.0.0)
